wdsdk/__init__.py
wdsdk/client.py
wdsdk/error.py
wdsdk/logger.py
wdsdk/request.py
wdsdk-0.0.4.dist-info/METADATA
wdsdk-0.0.4.dist-info/WHEEL
wdsdk-0.0.4.dist-info/top_level.txt
wdsdk-0.0.4.dist-info/RECORD
